visionframe/__init__.py
visionframe/extract_frames.py
visionframe/utils.py
visionframe-0.4.dist-info/LICENSE
visionframe-0.4.dist-info/METADATA
visionframe-0.4.dist-info/WHEEL
visionframe-0.4.dist-info/top_level.txt
visionframe-0.4.dist-info/RECORD
