Metadata-Version: 2.1
Name: visionframe
Version: 0.4
Summary: Empower Your Computer Vision Projects with VisionFrame: Seamlessly Handle Video and Image
Home-page: https://github.com/Applineed-AI/visionframe
Author: Md Faruk Alam
Author-email: farukalampro@gmail.com
License: MIT
License-File: LICENSE
Requires-Dist: tqdm
Requires-Dist: opencv-python
Requires-Dist: supervision ==0.9.0
